pomcorn/__init__.py
pomcorn/component.py
pomcorn/descriptors/__init__.py
pomcorn/descriptors/element.py
pomcorn/element.py
pomcorn/locators/__init__.py
pomcorn/locators/base_locators.py
pomcorn/locators/xpath_locators.py
pomcorn/page.py
pomcorn/py.typed
pomcorn/waits_conditions.py
pomcorn/web_view.py
pomcorn-0.9.3.dist-info/LICENSE
pomcorn-0.9.3.dist-info/METADATA
pomcorn-0.9.3.dist-info/WHEEL
pomcorn-0.9.3.dist-info/RECORD
