Metadata-Version: 2.1
Name: pomcorn
Version: 0.9.3
Summary: Base implementation of Page Object Model
Home-page: https://pypi.org/project/pomcorn/
License: MIT
Keywords: python,selenium,webdriver,autotests,page object model,page object pattern,page object,pom,parsing,browser
Author: Saritasa
Author-email: pypi@saritasa.com
Maintainer: Anton Oboleninov
Maintainer-email: anton.oboleninov@saritasa.com
Requires-Python: >=3.11,<4.0
Classifier: Development Status :: 4 - Beta
Classifier: Intended Audience :: Developers
Classifier: License :: OSI Approved :: MIT License
Classifier: Natural Language :: English
Classifier: Operating System :: OS Independent
Classifier: Programming Language :: Python :: 3
Classifier: Programming Language :: Python :: 3.11
Classifier: Programming Language :: Python :: 3.12
Classifier: Topic :: Software Development :: Libraries :: Python Modules
Requires-Dist: selenium (>=4.12)
Project-URL: Documentation, http://pomcorn.rtfd.io/
Project-URL: Repository, https://github.com/saritasa-nest/pomcorn/
